climbing_cams/__init__.py
climbing_cams/cam.py
climbing_cams/db.py
climbing_cams/plots.py
climbing_cams/rack.py
climbing_cams/units.py
climbing_cams/data/cams.csv
climbing_cams-0.0.3.dist-info/METADATA
climbing_cams-0.0.3.dist-info/WHEEL
climbing_cams-0.0.3.dist-info/licenses/LICENSE
climbing_cams-0.0.3.dist-info/RECORD
