Metadata-Version: 2.3
Name: climbing_cams
Version: 0.0.3
Summary: Tools for plotting statistics of climbing cams
Project-URL: Homepage, https://github.com/miguelmaso/climbing_cams
Project-URL: Repository, https://github.com/miguelmaso/climbing_cams
Author-email: Miguel Masó <miguel.maso@upc.edu>
License-Expression: MIT
License-File: LICENSE
Keywords: climbing,climbing cams,friends,rock climbing
Requires-Python: >=3
Requires-Dist: matplotlib
Requires-Dist: numpy
